pktai_tui/__init__.py
pktai_tui/app.py
pktai_tui/filtering.py
pktai_tui/models/__init__.py
pktai_tui/models/packet.py
pktai_tui/services/__init__.py
pktai_tui/services/agents.py
pktai_tui/services/capture.py
pktai_tui/services/config.py
pktai_tui/services/filtering.py
pktai_tui/services/llm.py
pktai_tui/ui/__init__.py
pktai_tui/ui/data_viewer.py
pktai_tui/ui/packet_list.py
pktai_tui/ui/settings.py
pktai-0.2.0.dist-info/METADATA
pktai-0.2.0.dist-info/WHEEL
pktai-0.2.0.dist-info/entry_points.txt
pktai-0.2.0.dist-info/licenses/LICENSE
pktai-0.2.0.dist-info/RECORD
