Metadata-Version: 2.4
Name: pktai
Version: 0.2.0
Summary: AI-assisted packet analysis in your terminal 🚀🤖📦💻
Project-URL: Homepage, https://github.com/kspviswa/pktai
Project-URL: Repository, https://github.com/kspviswa/pktai
Author: Viswa Kumar
License: MIT License
License-File: LICENSE
Requires-Python: >=3.10
Requires-Dist: openai>=1.30.0
Requires-Dist: pyshark>=0.6.0
Requires-Dist: pyyaml>=6.0.0
Requires-Dist: textual-fspicker>=0.4.0
Requires-Dist: textual>=0.70.0
Provides-Extra: dev
Requires-Dist: pytest>=8.4.1; extra == 'dev'
